{
  "id": "0x2275ec8",
  "kind": "TranslationUnitDecl",
  "loc": {},
  "range": {
    "begin": {},
    "end": {}
  },
  "inner": [
    {
      "id": "0x22766f0",
      "kind": "TypedefDecl",
      "loc": {},
      "range": {
        "begin": {},
        "end": {}
      },
      "isImplicit": true,
      "name": "__int128_t",
      "type": {
        "qualType": "__int128"
      },
      "inner": [
        {
          "id": "0x2276490",
          "kind": "BuiltinType",
          "type": {
            "qualType": "__int128"
          }
        }
      ]
    },
    {
      "id": "0x2276760",
      "kind": "TypedefDecl",
      "loc": {},
      "range": {
        "begin": {},
        "end": {}
      },
      "isImplicit": true,
      "name": "__uint128_t",
      "type": {
        "qualType": "unsigned __int128"
      },
      "inner": [
        {
          "id": "0x22764b0",
          "kind": "BuiltinType",
          "type": {
            "qualType": "unsigned __int128"
          }
        }
      ]
    },
    {
      "id": "0x2276a68",
      "kind": "TypedefDecl",
      "loc": {},
      "range": {
        "begin": {},
        "end": {}
      },
      "isImplicit": true,
      "name": "__NSConstantString",
      "type": {
        "qualType": "struct __NSConstantString_tag"
      },
      "inner": [
        {
          "id": "0x2276840",
          "kind": "RecordType",
          "type": {
            "qualType": "struct __NSConstantString_tag"
          },
          "decl": {
            "id": "0x22767b8",
            "kind": "RecordDecl",
            "name": "__NSConstantString_tag"
          }
        }
      ]
    },
    {
      "id": "0x2276b00",
      "kind": "TypedefDecl",
      "loc": {},
      "range": {
        "begin": {},
        "end": {}
      },
      "isImplicit": true,
      "name": "__builtin_ms_va_list",
      "type": {
        "qualType": "char *"
      },
      "inner": [
        {
          "id": "0x2276ac0",
          "kind": "PointerType",
          "type": {
            "qualType": "char *"
          },
          "inner": [
            {
              "id": "0x2275f70",
              "kind": "BuiltinType",
              "type": {
                "qualType": "char"
              }
            }
          ]
        }
      ]
    },
    {
      "id": "0x2276df8",
      "kind": "TypedefDecl",
      "loc": {},
      "range": {
        "begin": {},
        "end": {}
      },
      "isImplicit": true,
      "name": "__builtin_va_list",
      "type": {
        "qualType": "struct __va_list_tag[1]"
      },
      "inner": [
        {
          "id": "0x2276da0",
          "kind": "ConstantArrayType",
          "type": {
            "qualType": "struct __va_list_tag[1]"
          },
          "size": 1,
          "inner": [
            {
              "id": "0x2276be0",
              "kind": "RecordType",
              "type": {
                "qualType": "struct __va_list_tag"
              },
              "decl": {
                "id": "0x2276b58",
                "kind": "RecordDecl",
                "name": "__va_list_tag"
              }
            }
          ]
        }
      ]
    },
    {
      "id": "0x22db7a0",
      "kind": "VarDecl",
      "loc": {
        "offset": 4,
        "file": "/root/SYsU-lang/tester/function_test2020/10_if_else.sysu.c",
        "line": 1,
        "col": 5,
        "tokLen": 1
      },
      "range": {
        "begin": {
          "offset": 0,
          "col": 1,
          "tokLen": 3
        },
        "end": {
          "offset": 4,
          "col": 5,
          "tokLen": 1
        }
      },
      "isUsed": true,
      "name": "a",
      "mangledName": "a",
      "type": {
        "qualType": "int"
      }
    },
    {
      "id": "0x22db8a0",
      "kind": "FunctionDecl",
      "loc": {
        "offset": 11,
        "line": 2,
        "col": 5,
        "tokLen": 4
      },
      "range": {
        "begin": {
          "offset": 7,
          "col": 1,
          "tokLen": 3
        },
        "end": {
          "offset": 77,
          "line": 10,
          "col": 1,
          "tokLen": 1
        }
      },
      "name": "main",
      "mangledName": "main",
      "type": {
        "qualType": "int ()"
      },
      "inner": [
        {
          "id": "0x22dbad8",
          "kind": "CompoundStmt",
          "range": {
            "begin": {
              "offset": 17,
              "line": 2,
              "col": 11,
              "tokLen": 1
            },
            "end": {
              "offset": 77,
              "line": 10,
              "col": 1,
              "tokLen": 1
            }
          },
          "inner": [
            {
              "id": "0x22db980",
              "kind": "BinaryOperator",
              "range": {
                "begin": {
                  "offset": 20,
                  "line": 3,
                  "col": 2,
                  "tokLen": 1
                },
                "end": {
                  "offset": 24,
                  "col": 6,
                  "tokLen": 2
                }
              },
              "type": {
                "qualType": "int"
              },
              "valueCategory": "prvalue",
              "opcode": "=",
              "inner": [
                {
                  "id": "0x22db940",
                  "kind": "DeclRefExpr",
                  "range": {
                    "begin": {
                      "offset": 20,
                      "col": 2,
                      "tokLen": 1
                    },
                    "end": {
                      "offset": 20,
                      "col": 2,
                      "tokLen": 1
                    }
                  },
                  "type": {
                    "qualType": "int"
                  },
                  "valueCategory": "lvalue",
                  "referencedDecl": {
                    "id": "0x22db7a0",
                    "kind": "VarDecl",
                    "name": "a",
                    "type": {
                      "qualType": "int"
                    }
                  }
                },
                {
                  "id": "0x22db960",
                  "kind": "IntegerLiteral",
                  "range": {
                    "begin": {
                      "offset": 24,
                      "col": 6,
                      "tokLen": 2
                    },
                    "end": {
                      "offset": 24,
                      "col": 6,
                      "tokLen": 2
                    }
                  },
                  "type": {
                    "qualType": "int"
                  },
                  "valueCategory": "prvalue",
                  "value": "10"
                }
              ]
            },
            {
              "id": "0x22dbaa8",
              "kind": "IfStmt",
              "range": {
                "begin": {
                  "offset": 29,
                  "line": 4,
                  "col": 2,
                  "tokLen": 2
                },
                "end": {
                  "offset": 75,
                  "line": 9,
                  "col": 2,
                  "tokLen": 1
                }
              },
              "hasElse": true,
              "inner": [
                {
                  "id": "0x22db9f8",
                  "kind": "BinaryOperator",
                  "range": {
                    "begin": {
                      "offset": 33,
                      "line": 4,
                      "col": 6,
                      "tokLen": 1
                    },
                    "end": {
                      "offset": 35,
                      "col": 8,
                      "tokLen": 1
                    }
                  },
                  "type": {
                    "qualType": "int"
                  },
                  "valueCategory": "prvalue",
                  "opcode": ">",
                  "inner": [
                    {
                      "id": "0x22db9e0",
                      "kind": "ImplicitCastExpr",
                      "range": {
                        "begin": {
                          "offset": 33,
                          "col": 6,
                          "tokLen": 1
                        },
                        "end": {
                          "offset": 33,
                          "col": 6,
                          "tokLen": 1
                        }
                      },
                      "type": {
                        "qualType": "int"
                      },
                      "valueCategory": "prvalue",
                      "castKind": "LValueToRValue",
                      "inner": [
                        {
                          "id": "0x22db9a0",
                          "kind": "DeclRefExpr",
                          "range": {
                            "begin": {
                              "offset": 33,
                              "col": 6,
                              "tokLen": 1
                            },
                            "end": {
                              "offset": 33,
                              "col": 6,
                              "tokLen": 1
                            }
                          },
                          "type": {
                            "qualType": "int"
                          },
                          "valueCategory": "lvalue",
                          "referencedDecl": {
                            "id": "0x22db7a0",
                            "kind": "VarDecl",
                            "name": "a",
                            "type": {
                              "qualType": "int"
                            }
                          }
                        }
                      ]
                    },
                    {
                      "id": "0x22db9c0",
                      "kind": "IntegerLiteral",
                      "range": {
                        "begin": {
                          "offset": 35,
                          "col": 8,
                          "tokLen": 1
                        },
                        "end": {
                          "offset": 35,
                          "col": 8,
                          "tokLen": 1
                        }
                      },
                      "type": {
                        "qualType": "int"
                      },
                      "valueCategory": "prvalue",
                      "value": "0"
                    }
                  ]
                },
                {
                  "id": "0x22dba48",
                  "kind": "CompoundStmt",
                  "range": {
                    "begin": {
                      "offset": 38,
                      "col": 11,
                      "tokLen": 1
                    },
                    "end": {
                      "offset": 53,
                      "line": 6,
                      "col": 2,
                      "tokLen": 1
                    }
                  },
                  "inner": [
                    {
                      "id": "0x22dba38",
                      "kind": "ReturnStmt",
                      "range": {
                        "begin": {
                          "offset": 42,
                          "line": 5,
                          "col": 3,
                          "tokLen": 6
                        },
                        "end": {
                          "offset": 49,
                          "col": 10,
                          "tokLen": 1
                        }
                      },
                      "inner": [
                        {
                          "id": "0x22dba18",
                          "kind": "IntegerLiteral",
                          "range": {
                            "begin": {
                              "offset": 49,
                              "col": 10,
                              "tokLen": 1
                            },
                            "end": {
                              "offset": 49,
                              "col": 10,
                              "tokLen": 1
                            }
                          },
                          "type": {
                            "qualType": "int"
                          },
                          "valueCategory": "prvalue",
                          "value": "1"
                        }
                      ]
                    }
                  ]
                },
                {
                  "id": "0x22dba90",
                  "kind": "CompoundStmt",
                  "range": {
                    "begin": {
                      "offset": 60,
                      "line": 7,
                      "col": 6,
                      "tokLen": 1
                    },
                    "end": {
                      "offset": 75,
                      "line": 9,
                      "col": 2,
                      "tokLen": 1
                    }
                  },
                  "inner": [
                    {
                      "id": "0x22dba80",
                      "kind": "ReturnStmt",
                      "range": {
                        "begin": {
                          "offset": 64,
                          "line": 8,
                          "col": 3,
                          "tokLen": 6
                        },
                        "end": {
                          "offset": 71,
                          "col": 10,
                          "tokLen": 1
                        }
                      },
                      "inner": [
                        {
                          "id": "0x22dba60",
                          "kind": "IntegerLiteral",
                          "range": {
                            "begin": {
                              "offset": 71,
                              "col": 10,
                              "tokLen": 1
                            },
                            "end": {
                              "offset": 71,
                              "col": 10,
                              "tokLen": 1
                            }
                          },
                          "type": {
                            "qualType": "int"
                          },
                          "valueCategory": "prvalue",
                          "value": "0"
                        }
                      ]
                    }
                  ]
                }
              ]
            }
          ]
        }
      ]
    }
  ]
}